{
  "title": "校外教學到月球",
  "title2": "",
  "author": [
    {
      "author": "作者｜約翰．海爾",
      "info": [
        "出生於美國的繪本創作者約翰．海爾，同時是一位插畫家、設計師，太空迷。他最常用來創作的工具是便宜的鉛筆，說錯笑話的孩子、有長篇故事的老人家，以及被他惹惱的松鼠，都是他的靈感來源。",
        "",
        "《校外教學到月球》是他的第一本繪本創作，以寂靜的太空為發想，創造出充滿想像力的太空世界。繪本一推出就大受歡迎，獲頒「歐洲吹笛者文學獎」、「美國圖書館協會選書獎」、《學校圖書館學報》年度選書、《號角》雜誌年度選書、美國童書協會兒童選書獎等十一項國際獎項肯定，被翻譯為十三種語言版本。系列繪本有：《校外教學到海底》、《校外教學到火山》。",
        "",
        "目前他與妻子以及兩個小孩住在美國密蘇里州。"
      ]
    }
  ],
  "imgs": ["1F_MoonTrip1.jpg", "1F_MoonTrip2.jpg", "1F_MoonTrip3.jpg"],
  "copyright": "版權聲明：© 約翰．海爾，《校外教學到月球》，小麥田"
}
